aliyunsdkgreen/__init__.py
aliyunsdkgreen/endpoint.py
aliyunsdkgreen/request/__init__.py
aliyunsdkgreen/request/v20180509/AddFacesRequest.py
aliyunsdkgreen/request/v20180509/AddGroupsRequest.py
aliyunsdkgreen/request/v20180509/AddPersonRequest.py
aliyunsdkgreen/request/v20180509/AddSimilarityImageRequest.py
aliyunsdkgreen/request/v20180509/AddSimilarityLibraryRequest.py
aliyunsdkgreen/request/v20180509/AddVideoDnaGroupRequest.py
aliyunsdkgreen/request/v20180509/AddVideoDnaRequest.py
aliyunsdkgreen/request/v20180509/DeleteFacesRequest.py
aliyunsdkgreen/request/v20180509/DeleteGroupsRequest.py
aliyunsdkgreen/request/v20180509/DeletePersonRequest.py
aliyunsdkgreen/request/v20180509/DeleteSimilarityImageRequest.py
aliyunsdkgreen/request/v20180509/DeleteSimilarityLibraryRequest.py
aliyunsdkgreen/request/v20180509/DeleteVideoDnaGroupRequest.py
aliyunsdkgreen/request/v20180509/DeleteVideoDnaRequest.py
aliyunsdkgreen/request/v20180509/DetectFaceRequest.py
aliyunsdkgreen/request/v20180509/FileAsyncScanRequest.py
aliyunsdkgreen/request/v20180509/FileAsyncScanResultsRequest.py
aliyunsdkgreen/request/v20180509/FileAsyncScanV2Request.py
aliyunsdkgreen/request/v20180509/GetAddVideoDnaResultsRequest.py
aliyunsdkgreen/request/v20180509/GetFacesRequest.py
aliyunsdkgreen/request/v20180509/GetGroupsRequest.py
aliyunsdkgreen/request/v20180509/GetPersonRequest.py
aliyunsdkgreen/request/v20180509/GetPersonsRequest.py
aliyunsdkgreen/request/v20180509/GetSimilarityImageRequest.py
aliyunsdkgreen/request/v20180509/GetSimilarityLibraryRequest.py
aliyunsdkgreen/request/v20180509/ImageAsyncManualScanRequest.py
aliyunsdkgreen/request/v20180509/ImageAsyncManualScanResultsRequest.py
aliyunsdkgreen/request/v20180509/ImageAsyncScanRequest.py
aliyunsdkgreen/request/v20180509/ImageAsyncScanResultsRequest.py
aliyunsdkgreen/request/v20180509/ImageScanFeedbackRequest.py
aliyunsdkgreen/request/v20180509/ImageSyncScanRequest.py
aliyunsdkgreen/request/v20180509/ListSimilarityImagesRequest.py
aliyun_python_sdk_green-3.6.6.dist-info/LICENSE
aliyun_python_sdk_green-3.6.6.dist-info/METADATA
aliyun_python_sdk_green-3.6.6.dist-info/WHEEL
aliyun_python_sdk_green-3.6.6.dist-info/top_level.txt
aliyun_python_sdk_green-3.6.6.dist-info/RECORD
